k8s_explorer/__init__.py
k8s_explorer/cache.py
k8s_explorer/changes.py
k8s_explorer/client.py
k8s_explorer/config.py
k8s_explorer/filters.py
k8s_explorer/fuzzy_matching.py
k8s_explorer/models.py
k8s_explorer/permissions.py
k8s_explorer/prompts.py
k8s_explorer/py.typed
k8s_explorer/relationships.py
k8s_explorer/server.py
k8s_explorer/graph/__init__.py
k8s_explorer/graph/builder.py
k8s_explorer/graph/cache.py
k8s_explorer/graph/formatter.py
k8s_explorer/graph/models.py
k8s_explorer/graph/node_identity.py
k8s_explorer/graph/discoverers/__init__.py
k8s_explorer/graph/discoverers/custom.py
k8s_explorer/graph/discoverers/native.py
k8s_explorer/graph/discoverers/network.py
k8s_explorer/graph/discoverers/rbac.py
k8s_explorer/operators/__init__.py
k8s_explorer/operators/crd_handlers.py
k8s_explorer_mcp-0.1.3.dist-info/licenses/LICENSE
k8s_explorer_mcp-0.1.3.dist-info/METADATA
k8s_explorer_mcp-0.1.3.dist-info/WHEEL
k8s_explorer_mcp-0.1.3.dist-info/entry_points.txt
k8s_explorer_mcp-0.1.3.dist-info/top_level.txt
k8s_explorer_mcp-0.1.3.dist-info/RECORD
