Metadata-Version: 2.4
Name: k8s-explorer-mcp
Version: 0.1.3
Summary: Intelligent MCP server for Kubernetes resource exploration, relationship mapping, and debugging with AI-powered insights
Author: Nir Adler
Maintainer: Nir Adler
License: MIT
Project-URL: Homepage, https://github.com/nirwo/k8s-explorer-mcp
Project-URL: Documentation, https://github.com/nirwo/k8s-explorer-mcp/blob/main/README.md
Project-URL: Repository, https://github.com/nirwo/k8s-explorer-mcp
Project-URL: Issues, https://github.com/nirwo/k8s-explorer-mcp/issues
Project-URL: Changelog, https://github.com/nirwo/k8s-explorer-mcp/releases
Keywords: kubernetes,k8s,mcp,model-context-protocol,llm,ai,resource-management,devops,cloud-native,debugging,monitoring,kubectl,helm,argocd,operators
Classifier: Development Status :: 5 - Production/Stable
Classifier: Intended Audience :: Developers
Classifier: Intended Audience :: System Administrators
Classifier: License :: OSI Approved :: MIT License
Classifier: Operating System :: OS Independent
Classifier: Programming Language :: Python :: 3
Classifier: Programming Language :: Python :: 3.11
Classifier: Programming Language :: Python :: 3.12
Classifier: Programming Language :: Python :: 3.13
Classifier: Programming Language :: Python :: 3 :: Only
Classifier: Topic :: Software Development :: Libraries :: Python Modules
Classifier: Topic :: System :: Systems Administration
Classifier: Topic :: System :: Monitoring
Classifier: Environment :: Console
Classifier: Typing :: Typed
Requires-Python: >=3.11
License-File: LICENSE
Requires-Dist: fastmcp>=2.13.0.2
Requires-Dist: kubernetes>=34.1.0
Requires-Dist: cachetools>=6.2.1
Requires-Dist: pydantic>=2.12.4
Requires-Dist: aiohttp>=3.13.2
Requires-Dist: networkx>=3.5
Provides-Extra: dev
Requires-Dist: pytest>=8.4.2; extra == "dev"
Requires-Dist: pytest-asyncio>=1.2.0; extra == "dev"
Requires-Dist: black>=25.9.0; extra == "dev"
Requires-Dist: mypy>=1.18.2; extra == "dev"
Requires-Dist: ruff>=0.14.3; extra == "dev"
Dynamic: license-file
